tamil/__init__.py
tamil/stop_words.txt
tamil/vaaninlp.py
VaaniNLP-0.0.5.dist-info/LICENSE.txt
VaaniNLP-0.0.5.dist-info/METADATA
VaaniNLP-0.0.5.dist-info/WHEEL
VaaniNLP-0.0.5.dist-info/top_level.txt
VaaniNLP-0.0.5.dist-info/RECORD
